extraction/__init__.py
extraction/techniques.py
extraction/examples/__init__.py
extraction/examples/custom_technique.py
extraction/examples/new_return_type.py
extraction/tests/__init__.py
extraction/tests/data.py
extraction/tests/tests.py
extraction-0.3.dist-info/LICENSE.txt
extraction-0.3.dist-info/METADATA
extraction-0.3.dist-info/WHEEL
extraction-0.3.dist-info/top_level.txt
extraction-0.3.dist-info/RECORD
