Metadata-Version: 1.1
Name: extraction
Version: 0.3
Summary: Extract basic info from HTML webpages.
Home-page: http://pypi.python.org/pypi/extraction/
Author: Will Larson
Author-email: lethain@gmail.com
License: LICENSE.txt
Platform: UNKNOWN
Classifier: Programming Language :: Python :: 3
Classifier: License :: OSI Approved :: MIT License
Classifier: Operating System :: OS Independent
